json_stream_rs_tokenizer/__init__.py
json_stream_rs_tokenizer/json_stream_rs_tokenizer.pypy311-pp73-darwin.so
json_stream_rs_tokenizer/py.typed
json_stream_rs_tokenizer/json_stream_rs_tokenizer.pyi
json_stream_rs_tokenizer/benchmark/__init__.py
json_stream_rs_tokenizer/benchmark/random_json_generator.py
json_stream_rs_tokenizer/benchmark/cli.py
json_stream_rs_tokenizer/benchmark/app.py
json_stream_rs_tokenizer/benchmark/__main__.py
json_stream_rs_tokenizer-0.5.0.dist-info/RECORD
json_stream_rs_tokenizer-0.5.0.dist-info/WHEEL
json_stream_rs_tokenizer-0.5.0.dist-info/top_level.txt
json_stream_rs_tokenizer-0.5.0.dist-info/METADATA
json_stream_rs_tokenizer-0.5.0.dist-info/licenses/LICENSE
