Metadata-Version: 2.4
Name: json-stream-rs-tokenizer
Version: 0.5.0
Summary: A faster tokenizer for the json-stream Python library
Project-URL: Repository, https://github.com/smheidrich/py-json-stream-rs-tokenizer
Project-URL: Changelog, https://github.com/smheidrich/py-json-stream-rs-tokenizer/blob/main/CHANGELOG.md
Classifier: Programming Language :: Rust
Classifier: Programming Language :: Python :: Implementation :: CPython
Classifier: Programming Language :: Python :: Implementation :: PyPy
Classifier: Programming Language :: Python :: 3.8
Classifier: Programming Language :: Python :: 3.9
Classifier: Programming Language :: Python :: 3.10
Classifier: Programming Language :: Python :: 3.11
Classifier: Programming Language :: Python :: 3.12
Classifier: Programming Language :: Python :: 3.13
Classifier: Programming Language :: Python :: 3.14
Classifier: License :: OSI Approved :: MIT License
Requires-Python: >=3.8,<3.15
License-File: LICENSE
Provides-Extra: benchmark
Requires-Dist: json-stream-to-standard-types<0.2,>=0.1; extra == "benchmark"
Requires-Dist: tqdm<5,>=4.64; extra == "benchmark"
Requires-Dist: contexttimer<0.4,>=0.3; extra == "benchmark"
Requires-Dist: si-prefix<2,>=1.2; extra == "benchmark"
Requires-Dist: typer<0.7,>=0.6; extra == "benchmark"
Provides-Extra: test
Requires-Dist: pytest<8,>7.1; extra == "test"
Requires-Dist: json-stream-rs-tokenizer[benchmark]; extra == "test"
Requires-Dist: json-stream==2.3.2; extra == "test"
Provides-Extra: stubtest
Requires-Dist: mypy<2,>=1; extra == "stubtest"
Requires-Dist: types-tqdm; extra == "stubtest"
Dynamic: classifier
Dynamic: description
Dynamic: description-content-type
Dynamic: license-file
Dynamic: project-url
Dynamic: provides-extra
Dynamic: requires-python
Dynamic: summary
